MANIFEST.in
README.txt
ez_setup.py
setup.cfg
setup.py
examples/handbook/05_waves.py
examples/handbook/3D_02.py
examples/handbook/3D_03.py
examples/handbook/9-08.py
examples/handbook/9-09.py
examples/handbook/9-18.py
examples/handbook/centipede.py
examples/misc/boxandsphere.py
examples/misc/circles.py
examples/misc/coordsystem.py
examples/misc/falloff.py
examples/misc/fonttest.py
examples/misc/fpstest.py
examples/misc/helloworld.py
examples/misc/helloworldrot.py
examples/misc/orthoandperspective.py
examples/misc/piechart.py
examples/misc/polygons.py
examples/misc/recursion.py
examples/misc/triflower.py
examples/misc/widthandheight.py
examples/reference/ambientlight.py
examples/reference/applymatrix.py
examples/reference/arc.py
examples/reference/bezier.py
examples/reference/bezierdetail.py
examples/reference/bezierpoint.py
examples/reference/beziertangent.py
examples/reference/beziervertex.py
examples/reference/blendcolor.py
examples/reference/box.py
examples/reference/camera.py
examples/reference/colormode.py
examples/reference/cursor.py
examples/reference/curve.py
examples/reference/curvedetail.py
examples/reference/curvepoint.py
examples/reference/curvetangent.py
examples/reference/curvevertex.py
examples/reference/directionallight.py
examples/reference/ellipse.py
examples/reference/emissive.py
examples/reference/exit.py
examples/reference/get.py
examples/reference/keycode.py
examples/reference/keytyped.py
examples/reference/lerpcolor.py
examples/reference/lights.py
examples/reference/line.py
examples/reference/loadimage.py
examples/reference/loop.py
examples/reference/modelx.py
examples/reference/mousebutton.py
examples/reference/mouseclicked.py
examples/reference/mousedragged.py
examples/reference/mousemoved.py
examples/reference/nocursor.py
examples/reference/ortho.py
examples/reference/perspective.py
examples/reference/pimageset.py
examples/reference/pmousex.py
examples/reference/pointlight.py
examples/reference/popmatrix.py
examples/reference/rect.py
pyprocessing.egg-info/PKG-INFO
pyprocessing.egg-info/SOURCES.txt
pyprocessing.egg-info/dependency_links.txt
pyprocessing.egg-info/top_level.txt
