Metadata-Version: 1.0
Name: pyprocessing
Version: 0.1.2.7
Summary: A Processing-like environment for Python
Home-page: http://code.google.com/p/pyprocessing/
Author: Claudio Esperanca
Author-email: claudio.esperanca@gmail.com
License: BSD
Platform: UNKNOWN
